chainsaw/__init__.py
chainsaw/__main__.py
chainsaw/cli.py
chainsaw/configuration.py
chainsaw/effects.py
chainsaw/instruments.py
chainsaw/monitor.py
chainsaw/osc.py
chainsaw/tracks.py
chainsaw/utils.py
midi_chainsaw/__init__.py
midi_chainsaw/__main__.py
midi_chainsaw/mapping.py
midi_chainsaw/mapping_template.py
chainsaw_audio-0.3.3.dist-info/LICENSE
chainsaw_audio-0.3.3.dist-info/METADATA
chainsaw_audio-0.3.3.dist-info/WHEEL
chainsaw_audio-0.3.3.dist-info/entry_points.txt
chainsaw_audio-0.3.3.dist-info/top_level.txt
chainsaw_audio-0.3.3.dist-info/RECORD
