Metadata-Version: 2.1
Name: chainsaw-audio
Version: 0.3.3
Summary: Audio time-sampler and snapshot looper/granulator
Author-email: Grégory David <dev@groolot.net>, Jean-Emmanuel Doucet <jean-emmanuel.doucet@groolot.net>
Maintainer-email: Grégory David <dev@groolot.net>
License:                     GNU GENERAL PUBLIC LICENSE
Project-URL: Homepage, https://framagit.org/groolot-association/chainsaw
Project-URL: Bug Reports, https://framagit.org/groolot-association/chainsaw/-/issues
Project-URL: Source, https://framagit.org/groolot-association/chainsaw
Keywords: audio,sampler,looper,granulator
Classifier: Development Status :: 5 - Production/Stable
Classifier: License :: OSI Approved :: GNU General Public License v3 (GPLv3)
Classifier: Operating System :: POSIX :: Linux
Classifier: Programming Language :: Python :: 3
Classifier: Programming Language :: Python :: 3.7
Classifier: Programming Language :: Python :: 3.8
Classifier: Programming Language :: Python :: 3.9
Classifier: Programming Language :: Python :: 3.10
Classifier: Programming Language :: Python :: 3.11
Classifier: Programming Language :: Python :: 3 :: Only
Classifier: Topic :: Artistic Software
Classifier: Topic :: Multimedia :: Sound/Audio
Classifier: Topic :: Multimedia :: Sound/Audio :: Capture/Recording
Classifier: Topic :: Multimedia :: Sound/Audio :: MIDI
Requires-Python: <4,>=3.7
License-File: LICENSE
Requires-Dist: pyo>=1.0.4
Requires-Dist: mididings>=20230114
